Metadata-Version: 1.1
Name: supervisor-multiprocesslogging
Version: 1.1
Summary: Solve the problem of using supervisor to deploy tornado multiprocess log and cut it
Home-page: UNKNOWN
Author: xzregg
Author-email: xzregg@gmail.com
License: MIT Licence
Keywords: supervisor_multiprocesslogging,supervisor_multiprocesslogging
Platform: any
Requires: supervisor
